<?xml version="1.0" encoding="UTF-8"?>

<samplemap ID="XYLO 2" RRGroupAmount="1" MicPositions=";" SaveMode="2">
  <sample Root="72" LoKey="70" HiKey="75" LoVel="80" HiVel="127" RRGroup="1"
          FileName="{PROJECT_FOLDER}Xylophone/Medium Mallets/Xylo_Medium_C4_ff_01_far.wav"
          Duplicate="1" SampleStartMod="2000" Pan="-17" Volume="2" MonolithOffset="0"
          MonolithLength="151552" SampleRate="44100"/>
  <sample Root="72" LoKey="70" HiKey="75" LoVel="0" HiVel="80" RRGroup="1"
          FileName="{PROJECT_FOLDER}Xylophone/Medium Mallets/Xylo_Medium_C4_pp_01_far.wav"
          Duplicate="1" Volume="12" SampleStartMod="2000" Pan="-17" MonolithOffset="151552"
          MonolithLength="98304" SampleRate="44100"/>
  <sample Root="84" LoKey="82" HiKey="87" LoVel="80" HiVel="127" RRGroup="1"
          FileName="{PROJECT_FOLDER}Xylophone/Medium Mallets/Xylo_Medium_C5_ff_01_far.wav"
          Duplicate="1" SampleStartMod="2000" MonolithOffset="249856" MonolithLength="86016"
          SampleRate="44100"/>
  <sample Root="84" LoKey="82" HiKey="87" LoVel="0" HiVel="80" RRGroup="1"
          FileName="{PROJECT_FOLDER}Xylophone/Medium Mallets/Xylo_Medium_C5_pp_01_far.wav"
          Duplicate="1" Volume="10" SampleStartMod="2000" MonolithOffset="335872"
          MonolithLength="81920" SampleRate="44100"/>
  <sample Root="96" LoKey="94" HiKey="99" LoVel="80" HiVel="127" RRGroup="1"
          FileName="{PROJECT_FOLDER}Xylophone/Medium Mallets/Xylo_Medium_C6_ff_01_far.wav"
          Duplicate="1" SampleStartMod="2000" MonolithOffset="417792" MonolithLength="65536"
          SampleRate="44100"/>
  <sample Root="96" LoKey="94" HiKey="99" LoVel="0" HiVel="80" RRGroup="1"
          FileName="{PROJECT_FOLDER}Xylophone/Medium Mallets/Xylo_Medium_C6_pp_01_far.wav"
          Duplicate="1" Volume="10" SampleStartMod="2000" MonolithOffset="483328"
          MonolithLength="57344" SampleRate="44100"/>
  <sample Root="108" LoKey="106" HiKey="127" LoVel="80" HiVel="127" RRGroup="1"
          FileName="{PROJECT_FOLDER}Xylophone/Medium Mallets/Xylo_Medium_C7_ff_01_far.wav"
          Duplicate="1" SampleStartMod="2000" MonolithOffset="540672" MonolithLength="53248"
          SampleRate="44100"/>
  <sample Root="108" LoKey="106" HiKey="127" LoVel="0" HiVel="80" RRGroup="1"
          FileName="{PROJECT_FOLDER}Xylophone/Medium Mallets/Xylo_Medium_C7_pp_01_far.wav"
          Duplicate="1" Volume="10" SampleStartMod="2000" MonolithOffset="593920"
          MonolithLength="40960" SampleRate="44100"/>
  <sample Root="67" LoKey="0" HiKey="69" LoVel="0" HiVel="127" RRGroup="1"
          FileName="{PROJECT_FOLDER}Xylophone/Medium Mallets/Xylo_Medium_G3_pp_01_far.wav"
          Duplicate="1" Volume="12" SampleStartMod="2000" MonolithOffset="634880"
          MonolithLength="147456" SampleRate="44100"/>
  <sample Root="79" LoKey="76" HiKey="81" LoVel="80" HiVel="127" RRGroup="1"
          FileName="{PROJECT_FOLDER}Xylophone/Medium Mallets/Xylo_Medium_G4_ff_01_far.wav"
          Duplicate="1" SampleStartMod="2000" Pan="30" Volume="-1" MonolithOffset="782336"
          MonolithLength="114688" SampleRate="44100"/>
  <sample Root="79" LoKey="76" HiKey="81" LoVel="0" HiVel="80" RRGroup="1"
          FileName="{PROJECT_FOLDER}Xylophone/Medium Mallets/Xylo_Medium_G4_pp_01_far.wav"
          Duplicate="1" Volume="6" SampleStartMod="2000" Pan="40" MonolithOffset="897024"
          MonolithLength="94208" SampleRate="44100"/>
  <sample Root="91" LoKey="88" HiKey="93" LoVel="80" HiVel="127" RRGroup="1"
          FileName="{PROJECT_FOLDER}Xylophone/Medium Mallets/Xylo_Medium_G5_ff_01_far.wav"
          Duplicate="1" SampleStartMod="2000" Pan="25" MonolithOffset="991232"
          MonolithLength="73728" SampleRate="44100"/>
  <sample Root="91" LoKey="88" HiKey="93" LoVel="0" HiVel="80" RRGroup="1"
          FileName="{PROJECT_FOLDER}Xylophone/Medium Mallets/Xylo_Medium_G5_pp_01_far.wav"
          Duplicate="1" Volume="10" SampleStartMod="2000" Pan="25" MonolithOffset="1064960"
          MonolithLength="61440" SampleRate="44100"/>
  <sample Root="103" LoKey="100" HiKey="105" LoVel="80" HiVel="127" RRGroup="1"
          FileName="{PROJECT_FOLDER}Xylophone/Medium Mallets/Xylo_Medium_G6_ff_01_far.wav"
          Duplicate="1" SampleStartMod="2000" MonolithOffset="1126400"
          MonolithLength="61440" SampleRate="44100"/>
  <sample Root="103" LoKey="100" HiKey="105" LoVel="0" HiVel="80" RRGroup="1"
          FileName="{PROJECT_FOLDER}Xylophone/Medium Mallets/Xylo_Medium_G6_pp_01_far.wav"
          Duplicate="1" Volume="10" SampleStartMod="2000" MonolithOffset="1187840"
          MonolithLength="45056" SampleRate="44100"/>
</samplemap>
